setup.py
vp_probability_distributions/Binomialdistribution.py
vp_probability_distributions/Gaussiandistribution.py
vp_probability_distributions/Generaldistribution.py
vp_probability_distributions/__init__.py
vp_probability_distributions.egg-info/PKG-INFO
vp_probability_distributions.egg-info/SOURCES.txt
vp_probability_distributions.egg-info/dependency_links.txt
vp_probability_distributions.egg-info/not-zip-safe
vp_probability_distributions.egg-info/top_level.txt