Metadata-Version: 1.0
Name: vp-probability-distributions
Version: 0.1
Summary: Gaussian and Binomial distributions
Home-page: UNKNOWN
Author: Victor Pizarro
Author-email: v.pizarro@outlook.com
License: UNKNOWN
Platform: UNKNOWN
